prindent.py
prindent-1.0.1.dist-info/LICENSE
prindent-1.0.1.dist-info/METADATA
prindent-1.0.1.dist-info/WHEEL
prindent-1.0.1.dist-info/top_level.txt
prindent-1.0.1.dist-info/RECORD
