Metadata-Version: 2.1
Name: prindent
Version: 1.0.1
Summary: Print with auto indentation
Author-email: Gabriele Maurina <gabrielemaurina95@gmail.com>
Project-URL: Homepage, https://github.com/GabrieleMaurina/prindent
Classifier: Programming Language :: Python :: 3
Classifier: License :: OSI Approved :: GNU General Public License v3 (GPLv3)
Classifier: Operating System :: OS Independent
Requires-Python: >=3.7
License-File: LICENSE
